arc_agi_3/__init__.py
arc_agi_3/_agent.py
arc_agi_3/_cli.py
arc_agi_3/_recorder.py
arc_agi_3/_structs.py
arc_agi_3/_swarm.py
arc_agi_3/_tracing.py
arc_agi_3/templates/__init__.py
arc_agi_3/templates/_langgraph.py
arc_agi_3/templates/_llm.py
arc_agi_3/templates/_random.py
arc_agi_3/templates/_reasoning.py
arc_agi_3/templates/_smolagents.py
arc_agi_3-0.0.1.dist-info/METADATA
arc_agi_3-0.0.1.dist-info/WHEEL
arc_agi_3-0.0.1.dist-info/entry_points.txt
arc_agi_3-0.0.1.dist-info/RECORD
