Metadata-Version: 2.4
Name: arc-agi-3
Version: 0.0.1
Summary: Python SDK for building ARC-AGI-3 agents
Project-URL: Homepage, https://arcprize.org/
Project-URL: Repository, https://github.com/arcprize/ARC-AGI-3-Agents
Project-URL: Documentation, https://docs.arcprize.org/
Author: Jumyung Park, ARC Prize Foundation
License-Expression: MIT
Keywords: agents,ai,arc-agi,benchmark,reasoning
Classifier: Development Status :: 3 - Alpha
Classifier: Intended Audience :: Developers
Classifier: Intended Audience :: Science/Research
Classifier: License :: OSI Approved :: MIT License
Classifier: Programming Language :: Python :: 3
Classifier: Programming Language :: Python :: 3.12
Classifier: Programming Language :: Python :: 3.13
Classifier: Topic :: Scientific/Engineering :: Artificial Intelligence
Requires-Python: >=3.12
Requires-Dist: numpy>=2.0.0
Requires-Dist: pillow>=10.0.0
Requires-Dist: pydantic>=2.0.0
Requires-Dist: python-dotenv>=1.0.0
Requires-Dist: requests>=2.32.0
Provides-Extra: agentops
Requires-Dist: agentops>=0.4.0; extra == 'agentops'
Provides-Extra: all
Requires-Dist: agentops>=0.4.0; extra == 'all'
Requires-Dist: langchain-openai>=0.3.0; extra == 'all'
Requires-Dist: langchain>=0.3.0; extra == 'all'
Requires-Dist: langgraph-checkpoint-sqlite>=2.0.0; extra == 'all'
Requires-Dist: langgraph>=0.6.0; extra == 'all'
Requires-Dist: langsmith>=0.1.0; extra == 'all'
Requires-Dist: openai>=1.50.0; extra == 'all'
Requires-Dist: smolagents>=1.0.0; extra == 'all'
Provides-Extra: dev
Requires-Dist: mypy>=1.10.0; extra == 'dev'
Requires-Dist: pytest-asyncio>=0.23.0; extra == 'dev'
Requires-Dist: pytest>=8.0.0; extra == 'dev'
Requires-Dist: ruff>=0.5.0; extra == 'dev'
Provides-Extra: langgraph
Requires-Dist: langchain-openai>=0.3.0; extra == 'langgraph'
Requires-Dist: langchain>=0.3.0; extra == 'langgraph'
Requires-Dist: langgraph-checkpoint-sqlite>=2.0.0; extra == 'langgraph'
Requires-Dist: langgraph>=0.6.0; extra == 'langgraph'
Requires-Dist: langsmith>=0.1.0; extra == 'langgraph'
Provides-Extra: openai
Requires-Dist: openai>=1.50.0; extra == 'openai'
Provides-Extra: smolagents
Requires-Dist: smolagents>=1.0.0; extra == 'smolagents'
